testapp/__init__.py
testapp/mysdk.py
python_test_sdk_app-0.0.1.dist-info/LICENSE.txt
python_test_sdk_app-0.0.1.dist-info/METADATA
python_test_sdk_app-0.0.1.dist-info/WHEEL
python_test_sdk_app-0.0.1.dist-info/top_level.txt
python_test_sdk_app-0.0.1.dist-info/RECORD
