Metadata-Version: 2.1
Name: python-test-sdk-app
Version: 0.0.1
Summary: your module
Home-page: UNKNOWN
Author: Example Wmm 
License: UNKNOWN
Platform: UNKNOWN
Classifier: Programming Language :: Python
Classifier: Programming Language :: Python :: 3
License-File: LICENSE.txt
